{
  "Version": "2012-10-17",
  "Statement": [
    {
      "Effect": "Allow",
      "Action": [
        "route53resolver:*",
        "ec2:DescribeSubnets",
        "ec2:CreateNetworkInterface",
        "ec2:DeleteNetworkInterface",
        "ec2:ModifyNetworkInterfaceAttribute",
        "ec2:DescribeNetworkInterfaces",
        "ec2:CreateNetworkInterfacePermission",
        "ec2:DescribeSecurityGroups",
        "ec2:DescribeVpcs",
        "ec2:DescribeAvailabilityZones"
      ],
      "Resource": [
        "*"
      ]
    }
  ]
}