{
  "Version": "2012-10-17",
  "Statement": [
    {
      "Effect": "Allow",
      "Action": [
        "codepipeline:ListPipelineExecutions",
        "codepipeline:ListPipelines",
        "codepipeline:GetPipeline",
        "codepipeline:GetPipelineState",
        "codepipeline:GetPipelineExecution",
        "proton:GetAccountRoles",
        "proton:GetAccountSettings",
        "proton:GetEnvironment",
        "proton:GetEnvironmentAccountConnection",
        "proton:GetEnvironmentTemplate",
        "proton:GetEnvironmentTemplateMajorVersion",
        "proton:GetEnvironmentTemplateMinorVersion",
        "proton:GetEnvironmentTemplateVersion",
        "proton:GetRepository",
        "proton:GetRepositorySyncStatus",
        "proton:GetResourcesSummary",
        "proton:GetService",
        "proton:GetServiceInstance",
        "proton:GetServiceTemplate",
        "proton:GetServiceTemplateMajorVersion",
        "proton:GetServiceTemplateMinorVersion",
        "proton:GetServiceTemplateVersion",
        "proton:GetTemplateSyncConfig",
        "proton:GetTemplateSyncStatus",
        "proton:ListEnvironmentAccountConnections",
        "proton:ListEnvironmentOutputs",
        "proton:ListEnvironmentProvisionedResources",
        "proton:ListEnvironments",
        "proton:ListEnvironmentTemplateMajorVersions",
        "proton:ListEnvironmentTemplateMinorVersions",
        "proton:ListEnvironmentTemplates",
        "proton:ListEnvironmentTemplateVersions",
        "proton:ListRepositories",
        "proton:ListRepositorySyncDefinitions",
        "proton:ListServiceInstanceOutputs",
        "proton:ListServiceInstanceProvisionedResources",
        "proton:ListServiceInstances",
        "proton:ListServicePipelineOutputs",
        "proton:ListServicePipelineProvisionedResources",
        "proton:ListServices",
        "proton:ListServiceTemplateMajorVersions",
        "proton:ListServiceTemplateMinorVersions",
        "proton:ListServiceTemplates",
        "proton:ListServiceTemplateVersions",
        "proton:ListTagsForResource"
      ],
      "Resource": "*"
    }
  ]
}